mcp_spec_driven_development/__init__.py
mcp_spec_driven_development-0.1.0.dist-info/WHEEL
mcp_spec_driven_development-0.1.0.dist-info/entry_points.txt
mcp_spec_driven_development-0.1.0.dist-info/METADATA
mcp_spec_driven_development-0.1.0.dist-info/RECORD
