Metadata-Version: 2.3
Name: mcp-spec-driven-development
Version: 0.1.0
Summary: Add your description here
Author: lhy
Author-email: lhy <873904524@qq.com>
Requires-Dist: mcp[cli]>=1.12.2
Requires-Python: >=3.13
